odoo/addons/shopinvader_search_engine_update_pricelist/README.rst
odoo/addons/shopinvader_search_engine_update_pricelist/__init__.py
odoo/addons/shopinvader_search_engine_update_pricelist/__manifest__.py
odoo/addons/shopinvader_search_engine_update_pricelist/i18n/shopinvader_search_engine_update_pricelist.pot
odoo/addons/shopinvader_search_engine_update_pricelist/models/__init__.py
odoo/addons/shopinvader_search_engine_update_pricelist/models/product_pricelist.py
odoo/addons/shopinvader_search_engine_update_pricelist/readme/CONTEXT.md
odoo/addons/shopinvader_search_engine_update_pricelist/readme/CONTRIBUTORS.md
odoo/addons/shopinvader_search_engine_update_pricelist/readme/DESCRIPTION.md
odoo/addons/shopinvader_search_engine_update_pricelist/static/description/index.html
odoo/addons/shopinvader_search_engine_update_pricelist/tests/__init__.py
odoo/addons/shopinvader_search_engine_update_pricelist/tests/common.py
odoo/addons/shopinvader_search_engine_update_pricelist/tests/test_update.py
odoo_addon_shopinvader_search_engine_update_pricelist-16.0.1.0.0.2.dist-info/METADATA
odoo_addon_shopinvader_search_engine_update_pricelist-16.0.1.0.0.2.dist-info/WHEEL
odoo_addon_shopinvader_search_engine_update_pricelist-16.0.1.0.0.2.dist-info/top_level.txt
odoo_addon_shopinvader_search_engine_update_pricelist-16.0.1.0.0.2.dist-info/RECORD
